README.md
setup.py
smeftrunner/__init__.py
smeftrunner/beta.py
smeftrunner/classes.py
smeftrunner/cli.py
smeftrunner/definitions.py
smeftrunner/io.py
smeftrunner/rge.py
smeftrunner.egg-info/PKG-INFO
smeftrunner.egg-info/SOURCES.txt
smeftrunner.egg-info/dependency_links.txt
smeftrunner.egg-info/entry_points.txt
smeftrunner.egg-info/requires.txt
smeftrunner.egg-info/top_level.txt
smeftrunner/tests/data/Output_SMEFTrunner.dat
smeftrunner/tests/data/SMInput-CPV.dat
smeftrunner/tests/data/WCsInput-CPV-SMEFT.dat
smeftrunner/tests/data/betas_im.json
smeftrunner/tests/data/betas_re.json
smeftrunner/tests/data/random_par.json
smeftrunner/tests/data/random_wc.json