Metadata-Version: 1.0
Name: smeftrunner
Version: 2.1
Summary: A Python package for the renormalization group evolution in the Standard Model Effective Field Theory (SMEFT).
Home-page: https://github.com/DsixTools/python-smeftrunner
Author: Xuanyou Pan, David M. Straub
Author-email: xuanyou.pan@tum.de, david.straub@tum.de
License: MIT
Platform: UNKNOWN
